postmanparser/__init__.py
postmanparser/auth.py
postmanparser/certificate.py
postmanparser/collection.py
postmanparser/constants.py
postmanparser/cookie.py
postmanparser/description.py
postmanparser/event.py
postmanparser/exceptions.py
postmanparser/form_parameter.py
postmanparser/info.py
postmanparser/item.py
postmanparser/key_val.py
postmanparser/proxy_config.py
postmanparser/request.py
postmanparser/response.py
postmanparser/url.py
postmanparser/variable.py
postmanparser-0.1.9.dist-info/LICENSE.md
postmanparser-0.1.9.dist-info/METADATA
postmanparser-0.1.9.dist-info/WHEEL
postmanparser-0.1.9.dist-info/RECORD
