Metadata-Version: 2.3
Name: postmanparser
Version: 0.1.9
Summary: Postman collection parser for python
Home-page: https://github.com/appknox/postmanparser
License: Apache-2.0
Keywords: postman,appknox,postmanparser
Author: Appknox
Author-email: engineering@appknox.com
Requires-Python: >=3.8,<4.0
Classifier: Intended Audience :: Developers
Classifier: License :: OSI Approved :: Apache Software License
Classifier: Programming Language :: Python :: 3
Classifier: Programming Language :: Python :: 3.8
Classifier: Programming Language :: Python :: 3.9
Classifier: Programming Language :: Python :: 3.10
Classifier: Programming Language :: Python :: 3.11
Classifier: Programming Language :: Python :: 3.12
Classifier: Programming Language :: Python :: 3.13
Classifier: Topic :: Software Development :: Build Tools
Classifier: Topic :: Software Development :: Libraries :: Python Modules
Requires-Dist: httpx (>=0.27.0,<0.28.0)
Project-URL: Repository, https://github.com/appknox/postmanparser
